py.typed
investec_za_pb/__init__.py
investec_za_pb/_hooks/__init__.py
investec_za_pb/_hooks/clientcredentials.py
investec_za_pb/_hooks/registration.py
investec_za_pb/_hooks/sdkhooks.py
investec_za_pb/_hooks/types.py
investec_za_pb/_version.py
investec_za_pb/accounts.py
investec_za_pb/basesdk.py
investec_za_pb/beneficiaries.py
investec_za_pb/documents.py
investec_za_pb/httpclient.py
investec_za_pb/interaccounttransfers.py
investec_za_pb/models/__init__.py
investec_za_pb/models/accountsop.py
investec_za_pb/models/accountspendingtransactionsop.py
investec_za_pb/models/accountstransactionsop.py
investec_za_pb/models/apierror.py
investec_za_pb/models/authorisationsetupdetailsop.py
investec_za_pb/models/balanceop.py
investec_za_pb/models/beneficiariesop.py
investec_za_pb/models/beneficiarycategoriesop.py
investec_za_pb/models/documentop.py
investec_za_pb/models/documentsop.py
investec_za_pb/models/paybeneficiaryop.py
investec_za_pb/models/profileaccountsop.py
investec_za_pb/models/profilebenefiariesop.py
investec_za_pb/models/profilesop.py
investec_za_pb/models/security.py
investec_za_pb/models/transferop.py
investec_za_pb/models/transferv2op.py
investec_za_pb/profiles.py
investec_za_pb/py.typed
investec_za_pb/sdk.py
investec_za_pb/sdkconfiguration.py
investec_za_pb/types/__init__.py
investec_za_pb/types/basemodel.py
investec_za_pb/utils/__init__.py
investec_za_pb/utils/annotations.py
investec_za_pb/utils/enums.py
investec_za_pb/utils/eventstreaming.py
investec_za_pb/utils/forms.py
investec_za_pb/utils/headers.py
investec_za_pb/utils/logger.py
investec_za_pb/utils/metadata.py
investec_za_pb/utils/queryparams.py
investec_za_pb/utils/requestbodies.py
investec_za_pb/utils/retries.py
investec_za_pb/utils/security.py
investec_za_pb/utils/serializers.py
investec_za_pb/utils/url.py
investec_za_pb/utils/values.py
investec_za_pb-0.1.2.dist-info/METADATA
investec_za_pb-0.1.2.dist-info/WHEEL
investec_za_pb-0.1.2.dist-info/RECORD
